{"possibly_sensitive": false, "favorited": false, "truncated": false, "text": "La suerte gente me acompa\u00f1a siempre, vaya donde vaya. \nVoy a echar la loter\u00eda pero ya \ud83c\udf40\ud83c\udf40\ud83c\udf40\ud83c\udf40\ud83c\udf40\ud83c\udf40\ud83c\udf40\ud83c\udf40\ud83c\udf40\ud83c\udf40\ud83c\udf40\n( #IRONIA ) http://t.co/VrS3QaJfpr", "retweeted": false, "user": {"notifications": false, "profile_image_url_https": "https://pbs.twimg.com/profile_images/960965046984724482/zpDhBuDa_normal.jpg", "contributors_enabled": false, "profile_use_background_image": true, "followers_count": 198, "profile_image_url": "http://pbs.twimg.com/profile_images/960965046984724482/zpDhBuDa_normal.jpg", "utc_offset": null, "protected": false, "profile_banner_url": "https://pbs.twimg.com/profile_banners/544279601/1456062907", "profile_sidebar_border_color": "FFFFFF", "is_translation_enabled": false, "profile_background_image_url": "http://abs.twimg.com/images/themes/theme1/bg.png", "following": false, "screen_name": "srSadi12", "translator_type": "none", "follow_request_sent": false, "name": "SrSadi12", "time_zone": null, "friends_count": 514, "profile_text_color": "0084B4", "geo_enabled": true, "id": 544279601, "location": "Pac\u00edfico, Madrid", "default_profile_image": false, "profile_background_tile": true, "profile_sidebar_fill_color": "DDEEF6", "is_translator": false, "id_str": "544279601", "profile_background_image_url_https": "https://abs.twimg.com/images/themes/theme1/bg.png", "default_profile": false, "description": "vive el presente, olvida el pasado y espera el futuro.\nLove EDM-XSports-Futbol-Web's\n#ChalenciaIsReal", "statuses_count": 5675, "listed_count": 9, "entities": {"description": {"urls": []}}, "profile_link_color": "0333AD", "has_extended_profile": true, "url": null, "profile_background_color": "C0DEED", "lang": "es", "favourites_count": 3362, "verified": false, "created_at": "Tue Apr 03 13:41:53 +0000 2012"}, "id_str": "606150357010542592", "in_reply_to_status_id": null, "source": "<a href=\"http://twitter.com/download/android\" rel=\"nofollow\">Twitter for Android</a>", "place": {"bounding_box": {"type": "Polygon", "coordinates": [[[-3.8890049, 40.3120713], [-3.5180102, 40.3120713], [-3.5180102, 40.6435181], [-3.8890049, 40.6435181]]]}, "contained_within": [], "place_type": "city", "id": "206c436ce43a43a3", "country": "Spain", "url": "https://api.twitter.com/1.1/geo/id/206c436ce43a43a3.json", "name": "Madrid", "full_name": "Madrid, Spain", "attributes": {}, "country_code": "ES"}, "in_reply_to_status_id_str": null, "in_reply_to_user_id_str": null, "geo": null, "id": 606150357010542592, "in_reply_to_user_id": null, "contributors": null, "favorite_count": 0, "is_quote_status": false, "entities": {"urls": [], "user_mentions": [], "hashtags": [{"text": "IRONIA", "indices": [100, 107]}], "media": [{"expanded_url": "https://twitter.com/srSadi12/status/606150357010542592/photo/1", "sizes": {"medium": {"resize": "fit", "h": 854, "w": 480}, "small": {"resize": "fit", "h": 680, "w": 382}, "large": {"resize": "fit", "h": 854, "w": 480}, "thumb": {"resize": "crop", "h": 150, "w": 150}}, "id": 606150330884210688, "id_str": "606150330884210688", "media_url_https": "https://pbs.twimg.com/media/CGl6g7DWwAAe3Md.jpg", "url": "http://t.co/VrS3QaJfpr", "type": "photo", "media_url": "http://pbs.twimg.com/media/CGl6g7DWwAAe3Md.jpg", "indices": [110, 132], "display_url": "pic.twitter.com/VrS3QaJfpr"}], "symbols": []}, "extended_entities": {"media": [{"expanded_url": "https://twitter.com/srSadi12/status/606150357010542592/photo/1", "sizes": {"medium": {"resize": "fit", "h": 854, "w": 480}, "small": {"resize": "fit", "h": 680, "w": 382}, "large": {"resize": "fit", "h": 854, "w": 480}, "thumb": {"resize": "crop", "h": 150, "w": 150}}, "id": 606150330884210688, "id_str": "606150330884210688", "media_url_https": "https://pbs.twimg.com/media/CGl6g7DWwAAe3Md.jpg", "url": "http://t.co/VrS3QaJfpr", "type": "photo", "media_url": "http://pbs.twimg.com/media/CGl6g7DWwAAe3Md.jpg", "indices": [110, 132], "display_url": "pic.twitter.com/VrS3QaJfpr"}]}, "coordinates": null, "in_reply_to_screen_name": null, "lang": "es", "retweet_count": 0, "created_at": "Wed Jun 03 17:28:01 +0000 2015"}