{"favorited": false, "truncated": false, "text": "El romanticismo de mi enamorado, me conquista cada d\u00eda m\u00e1s. #Sarcasmo", "retweeted": false, "user": {"notifications": false, "profile_image_url_https": "https://pbs.twimg.com/profile_images/474265118771929088/F6Ql6-yH_normal.jpeg", "contributors_enabled": false, "profile_use_background_image": true, "followers_count": 299, "profile_image_url": "http://pbs.twimg.com/profile_images/474265118771929088/F6Ql6-yH_normal.jpeg", "utc_offset": null, "protected": false, "profile_banner_url": "https://pbs.twimg.com/profile_banners/54964151/1397450823", "profile_sidebar_border_color": "5ED4DC", "is_translation_enabled": false, "profile_background_image_url": "http://abs.twimg.com/images/themes/theme4/bg.gif", "following": false, "screen_name": "MsShishiH", "translator_type": "none", "follow_request_sent": false, "name": "Shishisaurus Rex", "time_zone": null, "friends_count": 703, "profile_text_color": "3C3940", "geo_enabled": true, "id": 54964151, "location": "Lima, Per\u00fa", "default_profile_image": false, "profile_background_tile": true, "profile_sidebar_fill_color": "95E8EC", "is_translator": false, "id_str": "54964151", "profile_background_image_url_https": "https://abs.twimg.com/images/themes/theme4/bg.gif", "default_profile": false, "description": "Girl. Geek. T-Rex. Day-Dreamer. 90s lover. Retro-gamer. Also, I'm half unicorn :)", "statuses_count": 6436, "listed_count": 5, "entities": {"description": {"urls": []}}, "profile_link_color": "0099B9", "has_extended_profile": false, "url": null, "profile_background_color": "0099B9", "lang": "es", "favourites_count": 2189, "verified": false, "created_at": "Wed Jul 08 17:29:32 +0000 2009"}, "id_str": "612061208238260224", "in_reply_to_status_id": null, "source": "<a href=\"http://twitter.com/download/android\" rel=\"nofollow\">Twitter for Android</a>", "place": {"bounding_box": {"type": "Polygon", "coordinates": [[[-76.9977230389369, -12.0877319713358], [-76.7837768396263, -12.0877319713358], [-76.7837768396263, -11.9934700172237], [-76.9977230389369, -11.9934700172237]]]}, "contained_within": [], "place_type": "city", "id": "0169e8f30556416d", "country": "Peru", "url": "https://api.twitter.com/1.1/geo/id/0169e8f30556416d.json", "name": "Ate", "full_name": "Ate, Peru", "attributes": {}, "country_code": "PE"}, "in_reply_to_status_id_str": null, "in_reply_to_user_id_str": null, "geo": {"type": "Point", "coordinates": [-12.0789363, -76.985325]}, "id": 612061208238260224, "in_reply_to_user_id": null, "contributors": null, "favorite_count": 0, "is_quote_status": false, "entities": {"urls": [], "user_mentions": [], "hashtags": [{"text": "Sarcasmo", "indices": [60, 69]}], "symbols": []}, "coordinates": {"type": "Point", "coordinates": [-76.985325, -12.0789363]}, "in_reply_to_screen_name": null, "lang": "es", "retweet_count": 0, "created_at": "Sat Jun 20 00:55:38 +0000 2015"}