{"possibly_sensitive": false, "favorited": false, "truncated": false, "text": "Nada como un domingo en el trabajo. \u270c #carrefour #ironia #sisepuede #domingo #junio https://t.co/dVhPIYd2qP", "retweeted": false, "user": {"notifications": false, "profile_image_url_https": "https://pbs.twimg.com/profile_images/817521729790734337/r9bw_kXk_normal.jpg", "contributors_enabled": false, "profile_use_background_image": true, "followers_count": 168, "profile_image_url": "http://pbs.twimg.com/profile_images/817521729790734337/r9bw_kXk_normal.jpg", "utc_offset": null, "protected": false, "profile_banner_url": "https://pbs.twimg.com/profile_banners/403082556/1520547784", "profile_sidebar_border_color": "FFFFFF", "is_translation_enabled": false, "profile_background_image_url": "http://abs.twimg.com/images/themes/theme1/bg.png", "following": false, "screen_name": "ftg1988", "translator_type": "none", "follow_request_sent": false, "name": "Francisco Tom\u00e1s", "time_zone": null, "friends_count": 411, "profile_text_color": "C7CAE3", "geo_enabled": true, "id": 403082556, "location": "Valencia, Espa\u00f1a", "default_profile_image": false, "profile_background_tile": true, "profile_sidebar_fill_color": "030303", "is_translator": false, "id_str": "403082556", "profile_background_image_url_https": "https://abs.twimg.com/images/themes/theme1/bg.png", "default_profile": false, "description": "Nunca te rindas, a veces la \u00faltima llave es la que abre la puerta.                                  \n\nInstagram: @francescotogue", "statuses_count": 5483, "listed_count": 1, "entities": {"description": {"urls": []}, "url": {"urls": [{"indices": [0, 23], "display_url": "facebook.com/profile.php?id\u2026", "expanded_url": "http://www.facebook.com/profile.php?id=121p0500684", "url": "https://t.co/nPprlGbcWF"}]}}, "profile_link_color": "7B7C82", "has_extended_profile": true, "url": "https://t.co/nPprlGbcWF", "profile_background_color": "C0DEED", "lang": "es", "favourites_count": 3847, "verified": false, "created_at": "Wed Nov 02 00:26:26 +0000 2011"}, "id_str": "612546634023616512", "in_reply_to_status_id": null, "source": "<a href=\"http://instagram.com\" rel=\"nofollow\">Instagram</a>", "place": null, "in_reply_to_status_id_str": null, "in_reply_to_user_id_str": null, "geo": null, "id": 612546634023616512, "in_reply_to_user_id": null, "contributors": null, "favorite_count": 0, "is_quote_status": false, "entities": {"urls": [{"indices": [84, 107], "display_url": "instagram.com/p/4L3xMUjDDy/", "expanded_url": "https://instagram.com/p/4L3xMUjDDy/", "url": "https://t.co/dVhPIYd2qP"}], "user_mentions": [], "hashtags": [{"text": "carrefour", "indices": [38, 48]}, {"text": "ironia", "indices": [49, 56]}, {"text": "sisepuede", "indices": [57, 67]}, {"text": "domingo", "indices": [68, 76]}, {"text": "junio", "indices": [77, 83]}], "symbols": []}, "coordinates": null, "in_reply_to_screen_name": null, "lang": "es", "retweet_count": 0, "created_at": "Sun Jun 21 09:04:32 +0000 2015"}