{"favorited": false, "truncated": false, "text": "Nuestro \"honorable\" Servicio de Administraci\u00f3n Tributaria hablando de orden y justicia. #Iron\u00eda", "retweeted": false, "user": {"notifications": false, "profile_image_url_https": "https://pbs.twimg.com/profile_images/941809268067418112/wY0RDxmO_normal.jpg", "contributors_enabled": false, "profile_use_background_image": true, "followers_count": 225, "profile_image_url": "http://pbs.twimg.com/profile_images/941809268067418112/wY0RDxmO_normal.jpg", "utc_offset": null, "protected": false, "profile_banner_url": "https://pbs.twimg.com/profile_banners/67147845/1465763143", "profile_sidebar_border_color": "C0DEED", "is_translation_enabled": false, "profile_background_image_url": "http://abs.twimg.com/images/themes/theme1/bg.png", "following": false, "screen_name": "Limonite78", "translator_type": "none", "follow_request_sent": false, "name": "Nadia", "time_zone": null, "friends_count": 178, "profile_text_color": "333333", "geo_enabled": true, "id": 67147845, "location": "Hermosillo", "default_profile_image": false, "profile_background_tile": false, "profile_sidebar_fill_color": "DDEEF6", "is_translator": false, "id_str": "67147845", "profile_background_image_url_https": "https://abs.twimg.com/images/themes/theme1/bg.png", "default_profile": true, "description": "Nac\u00ed el 13 de Agosto... \u00a1y soy orgullosamente zurda!", "statuses_count": 8727, "listed_count": 7, "entities": {"description": {"urls": []}}, "profile_link_color": "1DA1F2", "has_extended_profile": true, "url": null, "profile_background_color": "C0DEED", "lang": "en", "favourites_count": 8247, "verified": false, "created_at": "Wed Aug 19 22:46:03 +0000 2009"}, "id_str": "613860056333848576", "in_reply_to_status_id": null, "source": "<a href=\"http://twitter.com\" rel=\"nofollow\">Twitter Web Client</a>", "place": null, "in_reply_to_status_id_str": null, "in_reply_to_user_id_str": null, "geo": null, "id": 613860056333848576, "in_reply_to_user_id": null, "contributors": null, "favorite_count": 0, "is_quote_status": false, "entities": {"urls": [], "user_mentions": [], "hashtags": [{"text": "Iron\u00eda", "indices": [88, 95]}], "symbols": []}, "coordinates": null, "in_reply_to_screen_name": null, "lang": "es", "retweet_count": 0, "created_at": "Thu Jun 25 00:03:37 +0000 2015"}