{"favorited": false, "truncated": false, "text": "@RoalesAntonio @JuanEspadasSVQ  hay que recaudar hombre. No se ponga usted as\u00ed #ironia", "retweeted": false, "user": {"notifications": false, "profile_image_url_https": "https://pbs.twimg.com/profile_images/691636251154321409/ftRhwaX1_normal.jpg", "contributors_enabled": false, "profile_use_background_image": true, "followers_count": 488, "profile_image_url": "http://pbs.twimg.com/profile_images/691636251154321409/ftRhwaX1_normal.jpg", "utc_offset": null, "protected": false, "profile_banner_url": "https://pbs.twimg.com/profile_banners/1460011147/1503169533", "profile_sidebar_border_color": "FFFFFF", "is_translation_enabled": false, "profile_background_image_url": "http://abs.twimg.com/images/themes/theme1/bg.png", "following": false, "screen_name": "AlvaroLopezDC", "translator_type": "none", "follow_request_sent": false, "name": "\u00c1lvaro23", "time_zone": null, "friends_count": 478, "profile_text_color": "333333", "geo_enabled": false, "id": 1460011147, "location": "Sevilla, Andaluc\u00eda, Espa\u00f1a", "default_profile_image": false, "profile_background_tile": true, "profile_sidebar_fill_color": "DDEEF6", "is_translator": false, "id_str": "1460011147", "profile_background_image_url_https": "https://abs.twimg.com/images/themes/theme1/bg.png", "default_profile": false, "description": "El escudo del Betis debe estar siempre en el lado izquierdo de la camiseta, sobre el coraz\u00f3n (Sebasti\u00e1n Alabanda dixit) https://t.co/e6hAHvZb4N", "statuses_count": 27213, "listed_count": 10, "entities": {"description": {"urls": [{"indices": [120, 143], "display_url": "youtu.be/6HhhryEXXkI", "expanded_url": "http://youtu.be/6HhhryEXXkI", "url": "https://t.co/e6hAHvZb4N"}]}}, "profile_link_color": "00B300", "has_extended_profile": true, "url": null, "profile_background_color": "C0DEED", "lang": "es", "favourites_count": 2437, "verified": false, "created_at": "Sun May 26 15:55:08 +0000 2013"}, "id_str": "618703324011974656", "in_reply_to_status_id": 618702850634481664, "source": "<a href=\"http://twitter.com/download/android\" rel=\"nofollow\">Twitter for Android</a>", "place": null, "in_reply_to_status_id_str": "618702850634481664", "in_reply_to_user_id_str": "357786263", "geo": null, "id": 618703324011974656, "in_reply_to_user_id": 357786263, "contributors": null, "favorite_count": 1, "is_quote_status": false, "entities": {"urls": [], "user_mentions": [{"name": "Ecce Betis O\u00e9", "indices": [0, 14], "id": 357786263, "screen_name": "RoalesAntonio", "id_str": "357786263"}, {"name": "Juan Espadas Cejas", "indices": [15, 30], "id": 150584367, "screen_name": "JuanEspadasSVQ", "id_str": "150584367"}], "hashtags": [{"text": "ironia", "indices": [79, 86]}], "symbols": []}, "coordinates": null, "in_reply_to_screen_name": "RoalesAntonio", "lang": "es", "retweet_count": 0, "created_at": "Wed Jul 08 08:49:02 +0000 2015"}