{"favorited": false, "truncated": false, "text": "Tuve una semana hermosa #Sarcasmo", "retweeted": false, "user": {"notifications": false, "profile_image_url_https": "https://pbs.twimg.com/profile_images/830622149383708672/_fYpqTRO_normal.jpg", "contributors_enabled": false, "profile_use_background_image": true, "followers_count": 525, "profile_image_url": "http://pbs.twimg.com/profile_images/830622149383708672/_fYpqTRO_normal.jpg", "utc_offset": null, "protected": false, "profile_banner_url": "https://pbs.twimg.com/profile_banners/2461911128/1475172463", "profile_sidebar_border_color": "000000", "is_translation_enabled": false, "profile_background_image_url": "http://abs.twimg.com/images/themes/theme10/bg.gif", "following": false, "screen_name": "AgostinaFloress", "translator_type": "regular", "follow_request_sent": false, "name": "Pitufina \ud83d\udc51", "time_zone": null, "friends_count": 406, "profile_text_color": "333333", "geo_enabled": true, "id": 2461911128, "location": "En El Pais De Las Maravillas \u2665", "default_profile_image": false, "profile_background_tile": true, "profile_sidebar_fill_color": "DDEEF6", "is_translator": false, "id_str": "2461911128", "profile_background_image_url_https": "https://abs.twimg.com/images/themes/theme10/bg.gif", "default_profile": false, "description": "20. Patin Artistico. Belieber. San Lorenzo.\ud83d\udc99\u2764 29/06 \u2764 #20Nov insuperable", "statuses_count": 19003, "listed_count": 2, "entities": {"description": {"urls": []}, "url": {"urls": [{"indices": [0, 23], "display_url": "facebook.com/?q=#/AgoosBeLi\u2026", "expanded_url": "https://www.facebook.com/?q=#/AgoosBeLiieber?ref=tn_tnmn", "url": "https://t.co/Yxs9U9FFUw"}]}}, "profile_link_color": "9266CC", "has_extended_profile": true, "url": "https://t.co/Yxs9U9FFUw", "profile_background_color": "642D8B", "lang": "es", "favourites_count": 11391, "verified": false, "created_at": "Thu Apr 24 16:40:01 +0000 2014"}, "id_str": "622375770455961601", "in_reply_to_status_id": null, "source": "<a href=\"http://twitter.com/download/android\" rel=\"nofollow\">Twitter for Android</a>", "place": null, "in_reply_to_status_id_str": null, "in_reply_to_user_id_str": null, "geo": null, "id": 622375770455961601, "in_reply_to_user_id": null, "contributors": null, "favorite_count": 1, "is_quote_status": false, "entities": {"urls": [], "user_mentions": [], "hashtags": [{"text": "Sarcasmo", "indices": [24, 33]}], "symbols": []}, "coordinates": null, "in_reply_to_screen_name": null, "lang": "es", "retweet_count": 0, "created_at": "Sat Jul 18 12:02:01 +0000 2015"}