{"possibly_sensitive": false, "favorited": false, "truncated": false, "text": "Escucho a #macri y no puedo sacarme a los #simpsons d la cabeza.. #ironia #indiganada ACLARA Q NO OSCURECE MAN! http://t.co/CAJupou5Vv", "retweeted": false, "user": {"notifications": false, "profile_image_url_https": "https://pbs.twimg.com/profile_images/772249968832839680/YT4VeHzZ_normal.jpg", "contributors_enabled": false, "profile_use_background_image": true, "followers_count": 141, "profile_image_url": "http://pbs.twimg.com/profile_images/772249968832839680/YT4VeHzZ_normal.jpg", "utc_offset": null, "protected": false, "profile_banner_url": "https://pbs.twimg.com/profile_banners/213619732/1472953720", "profile_sidebar_border_color": "BDDCAD", "is_translation_enabled": false, "profile_background_image_url": "http://abs.twimg.com/images/themes/theme19/bg.gif", "following": false, "screen_name": "AllenFotografia", "translator_type": "none", "follow_request_sent": false, "name": "Gizulina", "time_zone": null, "friends_count": 26, "profile_text_color": "333333", "geo_enabled": false, "id": 213619732, "location": "Allen, Rio negro", "default_profile_image": false, "profile_background_tile": false, "profile_sidebar_fill_color": "DDFFCC", "is_translator": false, "id_str": "213619732", "profile_background_image_url_https": "https://abs.twimg.com/images/themes/theme19/bg.gif", "default_profile": false, "description": "Lo que viva en tu interior ser\u00e1 tu realidad..", "statuses_count": 486, "listed_count": 2, "entities": {"description": {"urls": []}}, "profile_link_color": "FF00E1", "has_extended_profile": false, "url": null, "profile_background_color": "FCDE65", "lang": "es", "favourites_count": 102, "verified": false, "created_at": "Tue Nov 09 11:21:35 +0000 2010"}, "id_str": "628748912409640960", "in_reply_to_status_id": null, "source": "<a href=\"http://twitter.com/download/android\" rel=\"nofollow\">Twitter for Android</a>", "place": null, "in_reply_to_status_id_str": null, "in_reply_to_user_id_str": null, "geo": null, "id": 628748912409640960, "in_reply_to_user_id": null, "contributors": null, "favorite_count": 0, "is_quote_status": false, "entities": {"urls": [], "user_mentions": [], "hashtags": [{"text": "macri", "indices": [10, 16]}, {"text": "simpsons", "indices": [42, 51]}, {"text": "ironia", "indices": [66, 73]}, {"text": "indiganada", "indices": [74, 85]}], "media": [{"expanded_url": "https://twitter.com/AllenFotografia/status/628748912409640960/photo/1", "sizes": {"medium": {"resize": "fit", "h": 640, "w": 650}, "small": {"resize": "fit", "h": 640, "w": 650}, "large": {"resize": "fit", "h": 640, "w": 650}, "thumb": {"resize": "crop", "h": 150, "w": 150}}, "id": 628748899663089664, "id_str": "628748899663089664", "media_url_https": "https://pbs.twimg.com/media/CLnDywFWEAAh1vx.jpg", "url": "http://t.co/CAJupou5Vv", "type": "photo", "media_url": "http://pbs.twimg.com/media/CLnDywFWEAAh1vx.jpg", "indices": [112, 134], "display_url": "pic.twitter.com/CAJupou5Vv"}], "symbols": []}, "extended_entities": {"media": [{"expanded_url": "https://twitter.com/AllenFotografia/status/628748912409640960/photo/1", "sizes": {"medium": {"resize": "fit", "h": 640, "w": 650}, "small": {"resize": "fit", "h": 640, "w": 650}, "large": {"resize": "fit", "h": 640, "w": 650}, "thumb": {"resize": "crop", "h": 150, "w": 150}}, "id": 628748899663089664, "id_str": "628748899663089664", "media_url_https": "https://pbs.twimg.com/media/CLnDywFWEAAh1vx.jpg", "url": "http://t.co/CAJupou5Vv", "type": "photo", "media_url": "http://pbs.twimg.com/media/CLnDywFWEAAh1vx.jpg", "indices": [112, 134], "display_url": "pic.twitter.com/CAJupou5Vv"}]}, "coordinates": null, "in_reply_to_screen_name": null, "lang": "es", "retweet_count": 0, "created_at": "Wed Aug 05 02:06:36 +0000 2015"}