{"lang": "es", "in_reply_to_screen_name": null, "retweet_count": 0, "id": 602549637355012097, "text": "Alguna de estas im\u00e1genes te sacara una sonrisa. \n#Humor #Sarcasmo #ViveFeliz #domingo #Relax #Diversi\u00f3n \nhttp://t.co/LqmV8iRO6V", "in_reply_to_user_id_str": null, "possibly_sensitive": false, "retweeted": false, "in_reply_to_status_id_str": null, "geo": null, "favorite_count": 0, "place": null, "created_at": "Sun May 24 19:00:03 +0000 2015", "id_str": "602549637355012097", "in_reply_to_status_id": null, "truncated": false, "source": "<a href=\"http://www.facebook.com/twitter\" rel=\"nofollow\">Facebook</a>", "coordinates": null, "entities": {"symbols": [], "urls": [{"expanded_url": "http://www.LittleClosetBoutique.com", "url": "http://t.co/LqmV8iRO6V", "indices": [105, 127], "display_url": "LittleClosetBoutique.com"}], "hashtags": [{"text": "Humor", "indices": [49, 55]}, {"text": "Sarcasmo", "indices": [56, 65]}, {"text": "ViveFeliz", "indices": [66, 76]}, {"text": "domingo", "indices": [77, 85]}, {"text": "Relax", "indices": [86, 92]}, {"text": "Diversi\u00f3n", "indices": [93, 103]}], "user_mentions": []}, "in_reply_to_user_id": null, "user": {"location": "Puerto Vallarta, Jalisco", "url": "https://t.co/qNR9jnXyKp", "lang": "es", "profile_banner_url": "https://pbs.twimg.com/profile_banners/2178658213/1467920966", "profile_background_image_url": "http://abs.twimg.com/images/themes/theme1/bg.png", "id": 2178658213, "friends_count": 994, "id_str": "2178658213", "profile_use_background_image": false, "profile_image_url": "http://pbs.twimg.com/profile_images/751133747655823360/Fa7JLsXe_normal.jpg", "profile_background_tile": false, "profile_text_color": "000000", "profile_sidebar_border_color": "000000", "profile_background_image_url_https": "https://abs.twimg.com/images/themes/theme1/bg.png", "notifications": false, "protected": false, "created_at": "Wed Nov 06 19:22:38 +0000 2013", "statuses_count": 21257, "follow_request_sent": false, "profile_sidebar_fill_color": "000000", "time_zone": null, "profile_link_color": "E81C4F", "following": false, "name": "Little Closet", "has_extended_profile": true, "contributors_enabled": false, "geo_enabled": true, "is_translation_enabled": false, "profile_background_color": "000000", "default_profile_image": false, "verified": false, "default_profile": false, "description": "Encuentra lo mejor de la moda! Enviamos a Todo Mexico y Vendemos Mayoreo. Env\u00edanos un Whatsapp 322 289 3655", "is_translator": false, "utc_offset": null, "screen_name": "LittleClosetMx", "listed_count": 7, "followers_count": 578, "translator_type": "none", "entities": {"url": {"urls": [{"expanded_url": "http://www.littleclosetboutique.com", "url": "https://t.co/qNR9jnXyKp", "indices": [0, 23], "display_url": "littleclosetboutique.com"}]}, "description": {"urls": []}}, "favourites_count": 6, "profile_image_url_https": "https://pbs.twimg.com/profile_images/751133747655823360/Fa7JLsXe_normal.jpg"}, "favorited": false, "is_quote_status": false, "contributors": null}