{"lang": "es", "in_reply_to_screen_name": null, "retweet_count": 0, "id": 603312842922659841, "text": "Este jueves a terminar los ex\u00e1menes y ver Transformers a la noche que la echan en la sexta, de tranquis\n#sarcasmo", "in_reply_to_user_id_str": null, "retweeted": false, "in_reply_to_status_id_str": null, "geo": null, "favorite_count": 1, "place": {"bounding_box": {"coordinates": [[[-4.3367625, 40.8348098], [-4.0524719, 40.8348098], [-4.0524719, 40.9888432], [-4.3367625, 40.9888432]]], "type": "Polygon"}, "full_name": "Segovia, Spain", "place_type": "city", "contained_within": [], "name": "Segovia", "country_code": "ES", "id": "3f632fe0c3770e29", "url": "https://api.twitter.com/1.1/geo/id/3f632fe0c3770e29.json", "attributes": {}, "country": "Spain"}, "created_at": "Tue May 26 21:32:45 +0000 2015", "id_str": "603312842922659841", "in_reply_to_status_id": null, "truncated": false, "source": "<a href=\"http://twitter.com/download/android\" rel=\"nofollow\">Twitter for Android</a>", "coordinates": null, "entities": {"symbols": [], "urls": [], "hashtags": [{"text": "sarcasmo", "indices": [104, 113]}], "user_mentions": []}, "in_reply_to_user_id": null, "user": {"location": "daqui' mismo", "url": null, "lang": "es", "profile_banner_url": "https://pbs.twimg.com/profile_banners/1897857890/1453214591", "profile_background_image_url": "http://abs.twimg.com/images/themes/theme1/bg.png", "id": 1897857890, "friends_count": 150, "id_str": "1897857890", "profile_use_background_image": true, "profile_image_url": "http://pbs.twimg.com/profile_images/415795309474623489/-PtD2pBC_normal.png", "profile_background_tile": false, "profile_text_color": "333333", "profile_sidebar_border_color": "C0DEED", "profile_background_image_url_https": "https://abs.twimg.com/images/themes/theme1/bg.png", "notifications": false, "protected": false, "created_at": "Mon Sep 23 17:03:01 +0000 2013", "statuses_count": 1406, "follow_request_sent": false, "profile_sidebar_fill_color": "DDEEF6", "time_zone": null, "profile_link_color": "1DA1F2", "following": false, "name": "deFrutos?", "has_extended_profile": true, "contributors_enabled": false, "geo_enabled": true, "is_translation_enabled": false, "profile_background_color": "C0DEED", "default_profile_image": false, "verified": false, "default_profile": true, "description": "Naciente un dia cualquiera del 97, subordinado a La Cristi y criado en el cercao' entre fogatas y chorizo marca Spar.", "is_translator": false, "utc_offset": null, "screen_name": "de_chunda", "listed_count": 1, "followers_count": 115, "translator_type": "none", "entities": {"description": {"urls": []}}, "favourites_count": 129, "profile_image_url_https": "https://pbs.twimg.com/profile_images/415795309474623489/-PtD2pBC_normal.png"}, "favorited": false, "is_quote_status": false, "contributors": null}