{"lang": "es", "in_reply_to_screen_name": null, "retweet_count": 0, "id": 604842469788921856, "text": "#Sarcasmo\n\n\"Encontrarla en este mundo me ser\u00e1 tan dif\u00edcil, para ello necesitar\u00e9 de la ayuda de un buen microscopio\" :D\n\nBuenas Noches!!", "in_reply_to_user_id_str": null, "retweeted": false, "in_reply_to_status_id_str": null, "geo": null, "favorite_count": 0, "place": null, "created_at": "Sun May 31 02:50:56 +0000 2015", "id_str": "604842469788921856", "in_reply_to_status_id": null, "truncated": false, "source": "<a href=\"http://www.facebook.com/twitter\" rel=\"nofollow\">Facebook</a>", "coordinates": null, "entities": {"symbols": [], "urls": [], "hashtags": [{"text": "Sarcasmo", "indices": [0, 9]}], "user_mentions": []}, "in_reply_to_user_id": null, "user": {"location": "San Salvador", "url": "https://t.co/R3xb7KXqZf", "lang": "es", "profile_banner_url": "https://pbs.twimg.com/profile_banners/364679999/1484321170", "profile_background_image_url": "http://abs.twimg.com/images/themes/theme1/bg.png", "id": 364679999, "friends_count": 521, "id_str": "364679999", "profile_use_background_image": true, "profile_image_url": "http://pbs.twimg.com/profile_images/1030155155231174656/gxpqwBjs_normal.jpg", "profile_background_tile": true, "profile_text_color": "333333", "profile_sidebar_border_color": "000000", "profile_background_image_url_https": "https://abs.twimg.com/images/themes/theme1/bg.png", "notifications": false, "protected": false, "created_at": "Tue Aug 30 04:30:16 +0000 2011", "statuses_count": 11836, "follow_request_sent": false, "profile_sidebar_fill_color": "DDEEF6", "time_zone": null, "profile_link_color": "FA743E", "following": false, "name": "Diego Roque", "has_extended_profile": true, "contributors_enabled": false, "geo_enabled": true, "is_translation_enabled": true, "profile_background_color": "FFFF00", "default_profile_image": false, "verified": false, "default_profile": false, "description": "", "is_translator": false, "utc_offset": null, "screen_name": "DiegoCideos", "listed_count": 5, "followers_count": 289, "translator_type": "none", "entities": {"url": {"urls": [{"expanded_url": "https://diegodelujan.blogspot.com/", "url": "https://t.co/R3xb7KXqZf", "indices": [0, 23], "display_url": "diegodelujan.blogspot.com"}]}, "description": {"urls": []}}, "favourites_count": 5075, "profile_image_url_https": "https://pbs.twimg.com/profile_images/1030155155231174656/gxpqwBjs_normal.jpg"}, "favorited": false, "is_quote_status": false, "contributors": null}