{"lang": "es", "in_reply_to_screen_name": null, "retweet_count": 0, "id": 607767604699267072, "text": "Y si mi sarcasmo le cae a usted,  aguanteselo,  no llor\u00e9,  no sea marica.\n\n#sarcasmo", "in_reply_to_user_id_str": null, "retweeted": false, "in_reply_to_status_id_str": null, "geo": null, "favorite_count": 0, "place": null, "created_at": "Mon Jun 08 04:34:23 +0000 2015", "id_str": "607767604699267072", "in_reply_to_status_id": null, "truncated": false, "source": "<a href=\"http://twitter.com/download/android\" rel=\"nofollow\">Twitter for Android</a>", "coordinates": null, "entities": {"symbols": [], "urls": [], "hashtags": [{"text": "sarcasmo", "indices": [75, 84]}], "user_mentions": []}, "in_reply_to_user_id": null, "user": {"location": "Colombia", "url": null, "lang": "es", "profile_banner_url": "https://pbs.twimg.com/profile_banners/1321338985/1402638171", "profile_background_image_url": "http://abs.twimg.com/images/themes/theme1/bg.png", "id": 1321338985, "friends_count": 387, "id_str": "1321338985", "profile_use_background_image": true, "profile_image_url": "http://pbs.twimg.com/profile_images/477817526748192768/m1c60_GQ_normal.jpeg", "profile_background_tile": true, "profile_text_color": "333333", "profile_sidebar_border_color": "000000", "profile_background_image_url_https": "https://abs.twimg.com/images/themes/theme1/bg.png", "notifications": false, "protected": false, "created_at": "Mon Apr 01 23:08:32 +0000 2013", "statuses_count": 910, "follow_request_sent": false, "profile_sidebar_fill_color": "DDEEF6", "time_zone": null, "profile_link_color": "0099B9", "following": false, "name": "El Bayron.", "has_extended_profile": false, "contributors_enabled": false, "geo_enabled": true, "is_translation_enabled": false, "profile_background_color": "FF0505", "default_profile_image": false, "verified": false, "default_profile": false, "description": "No hago muchos tuist pero los poco que hago valen la pena. #Whatsapp +57 3143593231 https://t.co/9QjgbsjefN  https://t.co/mRphbzgW4n", "is_translator": false, "utc_offset": null, "screen_name": "BaiironDiaz", "listed_count": 2, "followers_count": 694, "translator_type": "none", "entities": {"description": {"urls": [{"expanded_url": "http://facebook.com/Baiiron.Diiaz", "url": "https://t.co/9QjgbsjefN", "indices": [84, 107], "display_url": "facebook.com/Baiiron.Diiaz"}, {"expanded_url": "http://instagram.com/baiirondiaz", "url": "https://t.co/mRphbzgW4n", "indices": [109, 132], "display_url": "instagram.com/baiirondiaz"}]}}, "favourites_count": 79, "profile_image_url_https": "https://pbs.twimg.com/profile_images/477817526748192768/m1c60_GQ_normal.jpeg"}, "favorited": false, "is_quote_status": false, "contributors": null}