{"lang": "es", "in_reply_to_screen_name": null, "retweet_count": 0, "id": 610552171462033408, "text": "el fifa 16 QUE SORPRESA \n\n#sarcasmo", "in_reply_to_user_id_str": null, "retweeted": false, "in_reply_to_status_id_str": null, "geo": null, "favorite_count": 0, "place": null, "created_at": "Mon Jun 15 20:59:15 +0000 2015", "id_str": "610552171462033408", "in_reply_to_status_id": null, "truncated": false, "source": "<a href=\"http://twitter.com\" rel=\"nofollow\">Twitter Web Client</a>", "coordinates": null, "entities": {"symbols": [], "urls": [], "hashtags": [{"text": "sarcasmo", "indices": [26, 35]}], "user_mentions": []}, "in_reply_to_user_id": null, "user": {"location": "", "url": null, "lang": "es", "profile_banner_url": "https://pbs.twimg.com/profile_banners/1624458662/1524011743", "profile_background_image_url": "http://abs.twimg.com/images/themes/theme1/bg.png", "id": 1624458662, "friends_count": 137, "id_str": "1624458662", "profile_use_background_image": true, "profile_image_url": "http://pbs.twimg.com/profile_images/1027033842522185728/5hdMe1UJ_normal.jpg", "profile_background_tile": false, "profile_text_color": "333333", "profile_sidebar_border_color": "C0DEED", "profile_background_image_url_https": "https://abs.twimg.com/images/themes/theme1/bg.png", "notifications": false, "protected": false, "created_at": "Sat Jul 27 03:18:04 +0000 2013", "statuses_count": 7851, "follow_request_sent": false, "profile_sidebar_fill_color": "DDEEF6", "time_zone": null, "profile_link_color": "1DA1F2", "following": false, "name": "Spooky ROMAN12 (RORO)", "has_extended_profile": false, "contributors_enabled": false, "geo_enabled": false, "is_translation_enabled": false, "profile_background_color": "C0DEED", "default_profile_image": false, "verified": false, "default_profile": true, "description": "Futuro programador, lo de roro no se de donde mierda sacarlo pero es una parodia a jojo", "is_translator": false, "utc_offset": null, "screen_name": "romanzpon", "listed_count": 4, "followers_count": 57, "translator_type": "none", "entities": {"description": {"urls": []}}, "favourites_count": 7999, "profile_image_url_https": "https://pbs.twimg.com/profile_images/1027033842522185728/5hdMe1UJ_normal.jpg"}, "favorited": false, "is_quote_status": false, "contributors": null}