{"lang": "es", "in_reply_to_screen_name": null, "retweet_count": 0, "id": 614578731663757314, "text": "#Ironia todo el d\u00eda escuchando m\u00fasica Colombiana y en el f\u00fatbol apoyando a Messi y Mascherano de Argentina.", "in_reply_to_user_id_str": null, "retweeted": false, "in_reply_to_status_id_str": null, "geo": null, "favorite_count": 0, "place": {"bounding_box": {"coordinates": [[[-89.3507919, 12.984911], [-83.1355948, 12.984911], [-83.1355948, 17.417354], [-89.3507919, 17.417354]]], "type": "Polygon"}, "full_name": "Honduras", "place_type": "country", "contained_within": [], "name": "Honduras", "country_code": "HN", "id": "d862adecd71aa2a2", "url": "https://api.twitter.com/1.1/geo/id/d862adecd71aa2a2.json", "attributes": {}, "country": "Honduras"}, "created_at": "Fri Jun 26 23:39:22 +0000 2015", "id_str": "614578731663757314", "in_reply_to_status_id": null, "truncated": false, "source": "<a href=\"http://twitter.com/download/android\" rel=\"nofollow\">Twitter for Android</a>", "coordinates": null, "entities": {"symbols": [], "urls": [], "hashtags": [{"text": "Ironia", "indices": [0, 7]}], "user_mentions": []}, "in_reply_to_user_id": null, "user": {"location": "Santa Lucia F. M. Honduras", "url": null, "lang": "es", "profile_banner_url": "https://pbs.twimg.com/profile_banners/154159435/1401365638", "profile_background_image_url": "http://abs.twimg.com/images/themes/theme1/bg.png", "id": 154159435, "friends_count": 713, "id_str": "154159435", "profile_use_background_image": true, "profile_image_url": "http://pbs.twimg.com/profile_images/944677943669870593/_hnjNZM0_normal.jpg", "profile_background_tile": false, "profile_text_color": "666666", "profile_sidebar_border_color": "181A1E", "profile_background_image_url_https": "https://abs.twimg.com/images/themes/theme1/bg.png", "notifications": false, "protected": false, "created_at": "Thu Jun 10 14:44:28 +0000 2010", "statuses_count": 38324, "follow_request_sent": false, "profile_sidebar_fill_color": "252429", "time_zone": null, "profile_link_color": "2FC2EF", "following": false, "name": "Frank Godoy", "has_extended_profile": true, "contributors_enabled": false, "geo_enabled": true, "is_translation_enabled": false, "profile_background_color": "1A1B1F", "default_profile_image": false, "verified": false, "default_profile": false, "description": "#ViscaBarca #ViscaHonduras", "is_translator": false, "utc_offset": null, "screen_name": "Frankg1212", "listed_count": 10, "followers_count": 243, "translator_type": "none", "entities": {"description": {"urls": []}}, "favourites_count": 509, "profile_image_url_https": "https://pbs.twimg.com/profile_images/944677943669870593/_hnjNZM0_normal.jpg"}, "favorited": false, "is_quote_status": false, "contributors": null}