{"lang": "es", "in_reply_to_screen_name": "luistolito", "retweet_count": 0, "id": 616656971937251329, "text": "@luistolito @La_Renaixensa @fco_granaino @govern Con las facilidades del Estado supermegademocr\u00e1tico espa\u00f1ol ;) #ironia #modeon", "in_reply_to_user_id_str": "407267622", "retweeted": false, "in_reply_to_status_id_str": "616639300864765952", "geo": null, "favorite_count": 0, "place": null, "created_at": "Thu Jul 02 17:17:33 +0000 2015", "id_str": "616656971937251329", "in_reply_to_status_id": 616639300864765952, "truncated": false, "source": "<a href=\"http://twitter.com\" rel=\"nofollow\">Twitter Web Client</a>", "coordinates": null, "entities": {"symbols": [], "urls": [], "hashtags": [{"text": "ironia", "indices": [112, 119]}, {"text": "modeon", "indices": [120, 127]}], "user_mentions": [{"screen_name": "luistolito", "id": 407267622, "id_str": "407267622", "name": "Luis MS", "indices": [0, 11]}, {"screen_name": "La_Renaixensa", "id": 2390085684, "id_str": "2390085684", "name": "La Renaixen\u00e7a", "indices": [12, 26]}, {"screen_name": "fco_granaino", "id": 318556706, "id_str": "318556706", "name": "fco.molina_grana\u00edno", "indices": [27, 40]}, {"screen_name": "govern", "id": 145670919, "id_str": "145670919", "name": "Govern. Generalitat", "indices": [41, 48]}]}, "in_reply_to_user_id": 407267622, "user": {"location": "Catalunya/Catalu\u00f1a", "url": null, "lang": "en", "profile_banner_url": "https://pbs.twimg.com/profile_banners/3341678745/1467103142", "profile_background_image_url": "http://abs.twimg.com/images/themes/theme1/bg.png", "id": 3341678745, "friends_count": 233, "id_str": "3341678745", "profile_use_background_image": false, "profile_image_url": "http://pbs.twimg.com/profile_images/613653932062167040/48-yUI33_normal.png", "profile_background_tile": false, "profile_text_color": "000000", "profile_sidebar_border_color": "000000", "profile_background_image_url_https": "https://abs.twimg.com/images/themes/theme1/bg.png", "notifications": false, "protected": false, "created_at": "Mon Jun 22 17:08:15 +0000 2015", "statuses_count": 865, "follow_request_sent": false, "profile_sidebar_fill_color": "000000", "time_zone": null, "profile_link_color": "FA743E", "following": false, "name": "Estado Catal\u00e1n", "has_extended_profile": false, "contributors_enabled": false, "geo_enabled": false, "is_translation_enabled": false, "profile_background_color": "000000", "default_profile_image": false, "verified": false, "default_profile": false, "description": "En proceso ;) \nPromovent l'independentisme i lluitant contra els populistes de tots colors.", "is_translator": false, "utc_offset": null, "screen_name": "Estado_Catalan", "listed_count": 2, "followers_count": 58, "translator_type": "none", "entities": {"description": {"urls": []}}, "favourites_count": 258, "profile_image_url_https": "https://pbs.twimg.com/profile_images/613653932062167040/48-yUI33_normal.png"}, "favorited": false, "is_quote_status": false, "contributors": null}