{"quoted_status_id": 617933035900506112, "in_reply_to_screen_name": null, "retweet_count": 0, "id": 617942532261986304, "text": "jajaja lastima despues de esa lesion no volvera a ser un Crack! #Sarcasmo \n\n https://t.co/XrSCJlXba9", "in_reply_to_user_id_str": null, "possibly_sensitive": false, "retweeted": false, "user": {"location": "MEXICO", "url": null, "lang": "es", "profile_banner_url": "https://pbs.twimg.com/profile_banners/119794275/1453689006", "profile_background_image_url": "http://abs.twimg.com/images/themes/theme15/bg.png", "id": 119794275, "friends_count": 442, "id_str": "119794275", "profile_use_background_image": true, "profile_image_url": "http://pbs.twimg.com/profile_images/947520566881280000/xqz4Iw1A_normal.jpg", "profile_background_tile": false, "profile_text_color": "333333", "profile_sidebar_border_color": "FFFFFF", "profile_background_image_url_https": "https://abs.twimg.com/images/themes/theme15/bg.png", "notifications": false, "protected": false, "created_at": "Thu Mar 04 17:27:09 +0000 2010", "statuses_count": 51375, "follow_request_sent": false, "profile_sidebar_fill_color": "C0DFEC", "time_zone": null, "profile_link_color": "0084B4", "following": false, "name": "Enrique Valle", "has_extended_profile": true, "contributors_enabled": false, "geo_enabled": true, "is_translation_enabled": false, "profile_background_color": "022330", "default_profile_image": false, "verified": false, "default_profile": false, "description": "Dr en Medicina Forense,Cientifico y Psicologo Urbano, Apartidista,Democrata,Opinologo Gral Agnostico,a favor de la Eutanasia,y de un Mexico C/just.Social", "is_translator": false, "utc_offset": null, "screen_name": "drkevorkian_", "listed_count": 19, "followers_count": 870, "translator_type": "none", "entities": {"description": {"urls": []}}, "favourites_count": 1697, "profile_image_url_https": "https://pbs.twimg.com/profile_images/947520566881280000/xqz4Iw1A_normal.jpg"}, "in_reply_to_status_id_str": null, "geo": null, "lang": "es", "favorite_count": 1, "place": null, "created_at": "Mon Jul 06 06:25:55 +0000 2015", "id_str": "617942532261986304", "in_reply_to_status_id": null, "truncated": false, "source": "<a href=\"http://twitter.com\" rel=\"nofollow\">Twitter Web Client</a>", "coordinates": null, "entities": {"symbols": [], "urls": [{"expanded_url": "https://twitter.com/kalhua/status/617933035900506112", "url": "https://t.co/XrSCJlXba9", "indices": [77, 100], "display_url": "twitter.com/kalhua/status/\u2026"}], "hashtags": [{"text": "Sarcasmo", "indices": [64, 73]}], "user_mentions": []}, "in_reply_to_user_id": null, "quoted_status_id_str": "617933035900506112", "favorited": false, "quoted_status": {"extended_entities": {"media": [{"id_str": "617933026396221440", "media_url": "http://pbs.twimg.com/media/CJNW0EVUMAA16-s.jpg", "display_url": "pic.twitter.com/dUBQ9YikIc", "media_url_https": "https://pbs.twimg.com/media/CJNW0EVUMAA16-s.jpg", "type": "photo", "id": 617933026396221440, "url": "http://t.co/dUBQ9YikIc", "expanded_url": "https://twitter.com/kalhua/status/617933035900506112/photo/1", "indices": [35, 57], "sizes": {"medium": {"resize": "fit", "w": 720, "h": 422}, "large": {"resize": "fit", "w": 720, "h": 422}, "thumb": {"resize": "crop", "w": 150, "h": 150}, "small": {"resize": "fit", "w": 680, "h": 399}}}]}, "lang": "es", "in_reply_to_screen_name": "rinconderufo", "retweet_count": 3, "id": 617933035900506112, "text": "@rinconderufo Pobre del chicharito http://t.co/dUBQ9YikIc", "in_reply_to_user_id_str": "126445037", "possibly_sensitive": false, "retweeted": false, "in_reply_to_status_id_str": null, "geo": null, "favorite_count": 4, "place": null, "created_at": "Mon Jul 06 05:48:11 +0000 2015", "id_str": "617933035900506112", "in_reply_to_status_id": null, "truncated": false, "source": "<a href=\"http://twitter.com/download/iphone\" rel=\"nofollow\">Twitter for iPhone</a>", "coordinates": null, "entities": {"media": [{"id_str": "617933026396221440", "media_url": "http://pbs.twimg.com/media/CJNW0EVUMAA16-s.jpg", "display_url": "pic.twitter.com/dUBQ9YikIc", "media_url_https": "https://pbs.twimg.com/media/CJNW0EVUMAA16-s.jpg", "type": "photo", "id": 617933026396221440, "url": "http://t.co/dUBQ9YikIc", "expanded_url": "https://twitter.com/kalhua/status/617933035900506112/photo/1", "indices": [35, 57], "sizes": {"medium": {"resize": "fit", "w": 720, "h": 422}, "large": {"resize": "fit", "w": 720, "h": 422}, "thumb": {"resize": "crop", "w": 150, "h": 150}, "small": {"resize": "fit", "w": 680, "h": 399}}}], "symbols": [], "urls": [], "hashtags": [], "user_mentions": [{"screen_name": "rinconderufo", "id": 126445037, "id_str": "126445037", "name": "Adolfo D\u00edaz \"Rufo\"", "indices": [0, 13]}]}, "in_reply_to_user_id": 126445037, "user": {"location": "esperanza azul espa\u00f1a ", "url": null, "lang": "es", "profile_banner_url": "https://pbs.twimg.com/profile_banners/1609848727/1472799183", "profile_background_image_url": "http://abs.twimg.com/images/themes/theme1/bg.png", "id": 1609848727, "friends_count": 258, "id_str": "1609848727", "profile_use_background_image": true, "profile_image_url": "http://pbs.twimg.com/profile_images/775139437743177728/lv6I2M-W_normal.jpg", "profile_background_tile": false, "profile_text_color": "333333", "profile_sidebar_border_color": "C0DEED", "profile_background_image_url_https": "https://abs.twimg.com/images/themes/theme1/bg.png", "notifications": false, "protected": false, "created_at": "Sun Jul 21 05:49:22 +0000 2013", "statuses_count": 1149, "follow_request_sent": false, "profile_sidebar_fill_color": "DDEEF6", "time_zone": null, "profile_link_color": "1DA1F2", "following": false, "name": "DAVID.S \ud83c\ude50", "has_extended_profile": false, "contributors_enabled": false, "geo_enabled": false, "is_translation_enabled": false, "profile_background_color": "C0DEED", "default_profile_image": false, "verified": false, "default_profile": true, "description": "Soy responsable de lo que digo, no de lo que entiendes", "is_translator": false, "utc_offset": null, "screen_name": "kalhua", "listed_count": 19, "followers_count": 432, "translator_type": "none", "entities": {"description": {"urls": []}}, "favourites_count": 4856, "profile_image_url_https": "https://pbs.twimg.com/profile_images/775139437743177728/lv6I2M-W_normal.jpg"}, "favorited": false, "is_quote_status": false, "contributors": null}, "is_quote_status": true, "contributors": null}