{"lang": "es", "in_reply_to_screen_name": null, "retweet_count": 0, "id": 620831691188400128, "text": "Esta vez no s\u00e9 qu\u00e9 tuitear. Estoy destruida. Esta vida no vale nada. \u00bfPor qu\u00e9 yo?  \u00bfPor qu\u00e9 a m\u00ed?  #sufrimientofalso #sarcasmo #nomamar", "in_reply_to_user_id_str": null, "retweeted": false, "in_reply_to_status_id_str": null, "geo": null, "favorite_count": 0, "place": {"bounding_box": {"coordinates": [[[-99.6470277, 19.2156239], [-99.5128011, 19.2156239], [-99.5128011, 19.2874368], [-99.6470277, 19.2874368]]], "type": "Polygon"}, "full_name": "Metepec, M\u00e9xico", "place_type": "city", "contained_within": [], "name": "Metepec", "country_code": "MX", "id": "7bc29846eabda1f2", "url": "https://api.twitter.com/1.1/geo/id/7bc29846eabda1f2.json", "attributes": {}, "country": "Mexico"}, "created_at": "Tue Jul 14 05:46:24 +0000 2015", "id_str": "620831691188400128", "in_reply_to_status_id": null, "truncated": false, "source": "<a href=\"http://twitter.com/download/android\" rel=\"nofollow\">Twitter for Android</a>", "coordinates": null, "entities": {"symbols": [], "urls": [], "hashtags": [{"text": "sufrimientofalso", "indices": [99, 116]}, {"text": "sarcasmo", "indices": [117, 126]}, {"text": "nomamar", "indices": [127, 135]}], "user_mentions": []}, "in_reply_to_user_id": null, "user": {"location": "M\u00e9xico", "url": null, "lang": "es", "profile_banner_url": "https://pbs.twimg.com/profile_banners/261879930/1541291009", "profile_background_image_url": "http://abs.twimg.com/images/themes/theme1/bg.png", "id": 261879930, "friends_count": 619, "id_str": "261879930", "profile_use_background_image": true, "profile_image_url": "http://pbs.twimg.com/profile_images/1059300049417617409/ynSa7UcF_normal.jpg", "profile_background_tile": true, "profile_text_color": "333333", "profile_sidebar_border_color": "FFFFFF", "profile_background_image_url_https": "https://abs.twimg.com/images/themes/theme1/bg.png", "notifications": false, "protected": false, "created_at": "Sun Mar 06 22:12:18 +0000 2011", "statuses_count": 26713, "follow_request_sent": false, "profile_sidebar_fill_color": "DDEEF6", "time_zone": null, "profile_link_color": "DD2E44", "following": false, "name": "una P\u00e9rez", "has_extended_profile": false, "contributors_enabled": false, "geo_enabled": true, "is_translation_enabled": false, "profile_background_color": "528DAB", "default_profile_image": false, "verified": false, "default_profile": false, "description": "mujer.mexicana.amiga.hermana.hija.novia.22.aries", "is_translator": false, "utc_offset": null, "screen_name": "alesiram___", "listed_count": 5, "followers_count": 640, "translator_type": "none", "entities": {"description": {"urls": []}}, "favourites_count": 15708, "profile_image_url_https": "https://pbs.twimg.com/profile_images/1059300049417617409/ynSa7UcF_normal.jpg"}, "favorited": false, "is_quote_status": false, "contributors": null}