{"extended_entities": {"media": [{"id_str": "621910518148632577", "media_url": "http://pbs.twimg.com/media/CKF4UjxUEAERZ-6.jpg", "display_url": "pic.twitter.com/wCirehtklO", "media_url_https": "https://pbs.twimg.com/media/CKF4UjxUEAERZ-6.jpg", "type": "photo", "id": 621910518148632577, "url": "http://t.co/wCirehtklO", "expanded_url": "https://twitter.com/djhardcr/status/621910526512070656/photo/1", "indices": [118, 140], "sizes": {"large": {"resize": "fit", "w": 659, "h": 1024}, "thumb": {"resize": "crop", "w": 150, "h": 150}, "small": {"resize": "fit", "w": 438, "h": 680}, "medium": {"resize": "fit", "w": 659, "h": 1024}}}]}, "lang": "es", "in_reply_to_screen_name": null, "retweet_count": 0, "id": 621910526512070656, "text": "\ud83d\ude2bMae pero que preciosas se ven esas cdjs 2000nxs y por all\u00e1 ese djm 900nxs\ud83d\ude0f\ud83d\ude0f\ud83d\ude0f pero siaa la guila la cago\ud83d\ude29 #sarcasmo\ud83d\udc78\ud83d\ude3b http://t.co/wCirehtklO", "in_reply_to_user_id_str": null, "possibly_sensitive": false, "retweeted": false, "in_reply_to_status_id_str": null, "geo": null, "favorite_count": 1, "place": null, "created_at": "Fri Jul 17 05:13:18 +0000 2015", "id_str": "621910526512070656", "in_reply_to_status_id": null, "truncated": false, "source": "<a href=\"http://twitter.com/download/android\" rel=\"nofollow\">Twitter for Android</a>", "coordinates": null, "entities": {"media": [{"id_str": "621910518148632577", "media_url": "http://pbs.twimg.com/media/CKF4UjxUEAERZ-6.jpg", "display_url": "pic.twitter.com/wCirehtklO", "media_url_https": "https://pbs.twimg.com/media/CKF4UjxUEAERZ-6.jpg", "type": "photo", "id": 621910518148632577, "url": "http://t.co/wCirehtklO", "expanded_url": "https://twitter.com/djhardcr/status/621910526512070656/photo/1", "indices": [118, 140], "sizes": {"large": {"resize": "fit", "w": 659, "h": 1024}, "thumb": {"resize": "crop", "w": 150, "h": 150}, "small": {"resize": "fit", "w": 438, "h": 680}, "medium": {"resize": "fit", "w": 659, "h": 1024}}}], "symbols": [], "urls": [], "hashtags": [{"text": "sarcasmo", "indices": [106, 115]}], "user_mentions": []}, "in_reply_to_user_id": null, "user": {"location": "San Jos\u00e9, Costa Rica", "url": "https://t.co/5xRoR7Csus", "lang": "es", "profile_banner_url": "https://pbs.twimg.com/profile_banners/2252975065/1529443162", "profile_background_image_url": "http://abs.twimg.com/images/themes/theme9/bg.gif", "id": 2252975065, "friends_count": 176, "id_str": "2252975065", "profile_use_background_image": true, "profile_image_url": "http://pbs.twimg.com/profile_images/1009184056804667392/GL8Wl3Di_normal.jpg", "profile_background_tile": true, "profile_text_color": "000000", "profile_sidebar_border_color": "000000", "profile_background_image_url_https": "https://abs.twimg.com/images/themes/theme9/bg.gif", "notifications": false, "protected": false, "created_at": "Thu Dec 19 04:32:50 +0000 2013", "statuses_count": 22612, "follow_request_sent": false, "profile_sidebar_fill_color": "000000", "time_zone": null, "profile_link_color": "FAB81E", "following": false, "name": "H4RD", "has_extended_profile": true, "contributors_enabled": false, "geo_enabled": true, "is_translation_enabled": false, "profile_background_color": "ABB8C2", "default_profile_image": false, "verified": false, "default_profile": false, "description": "DJ / Apple Certified Technician / The Meeting Productions / hardBox / Snapchat: djhard / Instagram: @djhardcr", "is_translator": false, "utc_offset": null, "screen_name": "djhardcr", "listed_count": 7, "followers_count": 846, "translator_type": "regular", "entities": {"url": {"urls": [{"expanded_url": "https://www.themeetingcr.com/", "url": "https://t.co/5xRoR7Csus", "indices": [0, 23], "display_url": "themeetingcr.com"}]}, "description": {"urls": []}}, "favourites_count": 10436, "profile_image_url_https": "https://pbs.twimg.com/profile_images/1009184056804667392/GL8Wl3Di_normal.jpg"}, "favorited": false, "is_quote_status": false, "contributors": null}